README.md
setup.py
aud/__init__.pyi
aud/py.typed
bge/__init__.pyi
bge/app.pyi
bge/constraints.pyi
bge/events.pyi
bge/logic.pyi
bge/py.typed
bge/render.pyi
bge/texture.pyi
bge/types.pyi
bgl/__init__.pyi
bgl/py.typed
bl_math/__init__.pyi
bl_math/py.typed
blf/__init__.pyi
blf/py.typed
bmesh/__init__.pyi
bmesh/geometry.pyi
bmesh/ops.pyi
bmesh/py.typed
bmesh/types.pyi
bmesh/utils.pyi
bpy/__init__.pyi
bpy/context.pyi
bpy/msgbus.pyi
bpy/path.pyi
bpy/props.pyi
bpy/py.typed
bpy/types.pyi
bpy/app/__init__.pyi
bpy/app/handlers.pyi
bpy/app/icons.pyi
bpy/app/timers.pyi
bpy/app/translations.pyi
bpy/ops/__init__.pyi
bpy/ops/action.pyi
bpy/ops/anim.pyi
bpy/ops/armature.pyi
bpy/ops/asset.pyi
bpy/ops/boid.pyi
bpy/ops/brush.pyi
bpy/ops/buttons.pyi
bpy/ops/cachefile.pyi
bpy/ops/camera.pyi
bpy/ops/clip.pyi
bpy/ops/cloth.pyi
bpy/ops/collection.pyi
bpy/ops/console.pyi
bpy/ops/constraint.pyi
bpy/ops/curve.pyi
bpy/ops/cycles.pyi
bpy/ops/dpaint.pyi
bpy/ops/ed.pyi
bpy/ops/export_anim.pyi
bpy/ops/export_mesh.pyi
bpy/ops/export_scene.pyi
bpy/ops/file.pyi
bpy/ops/fluid.pyi
bpy/ops/font.pyi
bpy/ops/geometry.pyi
bpy/ops/gizmogroup.pyi
bpy/ops/gpencil.pyi
bpy/ops/graph.pyi
bpy/ops/image.pyi
bpy/ops/import_anim.pyi
bpy/ops/import_curve.pyi
bpy/ops/import_mesh.pyi
bpy/ops/import_scene.pyi
bpy/ops/info.pyi
bpy/ops/lattice.pyi
bpy/ops/logic.pyi
bpy/ops/marker.pyi
bpy/ops/mask.pyi
bpy/ops/material.pyi
bpy/ops/mball.pyi
bpy/ops/mesh.pyi
bpy/ops/nla.pyi
bpy/ops/node.pyi
bpy/ops/object.pyi
bpy/ops/outliner.pyi
bpy/ops/paint.pyi
bpy/ops/paintcurve.pyi
bpy/ops/palette.pyi
bpy/ops/particle.pyi
bpy/ops/pose.pyi
bpy/ops/poselib.pyi
bpy/ops/preferences.pyi
bpy/ops/ptcache.pyi
bpy/ops/render.pyi
bpy/ops/rigidbody.pyi
bpy/ops/safe_areas.pyi
bpy/ops/scene.pyi
bpy/ops/screen.pyi
bpy/ops/script.pyi
bpy/ops/sculpt.pyi
bpy/ops/sequencer.pyi
bpy/ops/sound.pyi
bpy/ops/spreadsheet.pyi
bpy/ops/surface.pyi
bpy/ops/text.pyi
bpy/ops/texture.pyi
bpy/ops/transform.pyi
bpy/ops/ui.pyi
bpy/ops/uv.pyi
bpy/ops/view2d.pyi
upbge_stubs.egg-info/PKG-INFO
upbge_stubs.egg-info/SOURCES.txt
upbge_stubs.egg-info/dependency_links.txt
upbge_stubs.egg-info/not-zip-safe
upbge_stubs.egg-info/top_level.txt